microblog/__init__.py
microblog/cli.py
microblog/logging.py
microblog/renderers.py
microblog/repo.py
pelican/plugins/microblog/__init__.py
microblog_git-0.10.0.dist-info/LICENSE
microblog_git-0.10.0.dist-info/METADATA
microblog_git-0.10.0.dist-info/WHEEL
microblog_git-0.10.0.dist-info/entry_points.txt
microblog_git-0.10.0.dist-info/top_level.txt
microblog_git-0.10.0.dist-info/RECORD
