Metadata-Version: 2.1
Name: microblog-git
Version: 0.10.0
Summary: Python renderer for git microblogs
Home-page: https://github.com/sio/microblog-python
License: Apache-2.0
Keywords: blog,microblog,git
Classifier: Environment :: Console
Classifier: Intended Audience :: Developers
Classifier: License :: OSI Approved :: Apache Software License
License-File: LICENSE
Requires-Dist: GitPython
Requires-Dist: markdown
Requires-Dist: pymdown-extensions
Requires-Dist: toml
